rinexmod/__init__.py
rinexmod/metadata.py
rinexmod/rinexfile.py
rinexmod/rinexmod_api.py
rinexmod/api/__init__.py
rinexmod/api/core_fcts.py
rinexmod/api/rinexmod_cli.py
rinexmod/api/rinexmod_main.py
rinexmod/bin/__init__.py
rinexmod/bin/rinexmod_run.py
rinexmod/bin/misc_tools/__init__.py
rinexmod/bin/misc_tools/crzmeta.py
rinexmod/bin/misc_tools/get_m3g_sitelogs.py
rinexmod/bin/misc_tools/rinexrename.py
rinexmod/classes/__init__.py
rinexmod/classes/metadata.py
rinexmod/classes/rinexfile.py
rinexmod/common/__init__.py
rinexmod/common/gamit_meta.py
rinexmod/logger/__init__.py
rinexmod/logger/logger.py
rinexmod-4.0.1.dist-info/licenses/LICENSE
rinexmod-4.0.1.dist-info/METADATA
rinexmod-4.0.1.dist-info/WHEEL
rinexmod-4.0.1.dist-info/entry_points.txt
rinexmod-4.0.1.dist-info/top_level.txt
rinexmod-4.0.1.dist-info/RECORD
