Metadata-Version: 2.4
Name: rinexmod
Version: 4.0.1
Summary: Tool to batch modify headers of RINEX Hatanaka compressed files.
Author-email: Pierre Sakic <sakic@ipgp.fr>
License-Expression: GPL-3.0-or-later
Project-URL: Homepage, https://github.com/IPGP/rinexmod
Keywords: geodesy,gnss,rinex,header,metadata,positioning
Classifier: Development Status :: 3 - Alpha
Classifier: Development Status :: 4 - Beta
Classifier: Intended Audience :: Science/Research
Classifier: Programming Language :: Python :: 3
Classifier: Programming Language :: Python :: 3.9
Classifier: Programming Language :: Python :: 3.10
Classifier: Programming Language :: Python :: 3.11
Classifier: Programming Language :: Python :: 3.12
Classifier: Programming Language :: Python :: 3.13
Classifier: Programming Language :: Python :: 3 :: Only
Requires-Python: <4,>=3.5
License-File: LICENSE
Requires-Dist: colorlog
Requires-Dist: pandas
Requires-Dist: hatanaka
Requires-Dist: numpy
Requires-Dist: requests
Requires-Dist: setuptools
Requires-Dist: pycountry
Dynamic: license-file
